spirit_link/__init__.py
spirit_link/cmd.py
spirit_link/descriptors.py
spirit_link/backends/__init__.py
spirit_link/backends/dot.py
spirit_link-0.1.dist-info/LICENSE
spirit_link-0.1.dist-info/METADATA
spirit_link-0.1.dist-info/WHEEL
spirit_link-0.1.dist-info/entry_points.txt
spirit_link-0.1.dist-info/top_level.txt
spirit_link-0.1.dist-info/RECORD
