Metadata-Version: 2.1
Name: spirit-link
Version: 0.1
Home-page: https://github.com/Suzhou-Tongyuan/spirit-link
Author: TongYuan
Author-email: support@tongyuan.cc
License: mit
Platform: any
Classifier: Programming Language :: Python :: 3.9
Classifier: Programming Language :: Python :: 3.10
Classifier: Programming Language :: Python :: Implementation :: CPython
Requires-Python: >=3.6.0
License-File: LICENSE
Requires-Dist: wisepy2
Requires-Dist: graphviz-artist
Requires-Dist: colorama
